pyspray/__init__.py
pyspray/__main__.py
pyspray/benchmark.py
pyspray/gif_display.py
pyspray/image_fetching.py
pyspray/vmt.py
pyspray/vtf.py
pyspray-0.0.12.dist-info/LICENSE
pyspray-0.0.12.dist-info/METADATA
pyspray-0.0.12.dist-info/WHEEL
pyspray-0.0.12.dist-info/top_level.txt
pyspray-0.0.12.dist-info/RECORD
