Metadata-Version: 2.1
Name: pyspray
Version: 0.0.12
Summary: A CLI interface for quickly making sprays for Team Fortress 2.
Author-email: sillysandvich <teamfortress.stupid@gmail.com>
License: # Gay Agenda License - 1.0
Project-URL: Homepage, https://github.com/sillysandvich/pyspray
Classifier: Programming Language :: Python :: 3
Classifier: Operating System :: OS Independent
Requires-Python: >=3.8
License-File: LICENSE
Requires-Dist: certifi ==2024.7.4
Requires-Dist: charset-normalizer ==3.3.2
Requires-Dist: click ==8.1.7
Requires-Dist: colorama ==0.4.6
Requires-Dist: idna ==3.7
Requires-Dist: numpy ==2.0.1
Requires-Dist: opencv-python ==4.10.0.84
Requires-Dist: pillow ==10.4.0
Requires-Dist: quicktex ==0.2.1
Requires-Dist: requests ==2.32.3
Requires-Dist: urllib3 ==2.2.2
